deepjson_py_connector/__init__.py
deepjson_py_connector/client.py
deepjson_py_connector-0.1.1.dist-info/licenses/LICENSE
deepjson_py_connector-0.1.1.dist-info/METADATA
deepjson_py_connector-0.1.1.dist-info/WHEEL
deepjson_py_connector-0.1.1.dist-info/top_level.txt
deepjson_py_connector-0.1.1.dist-info/RECORD
