Metadata-Version: 2.4
Name: deepjson-py-connector
Version: 0.1.1
Summary: Python connector for DeepJSON server
Author-email: Eren Havuc <e.havuc@draykant.eu>
License-Expression: MIT
Requires-Python: >=3.7
License-File: LICENSE
Requires-Dist: requests>=2.25
Requires-Dist: requests-toolbelt>=0.9.1
Dynamic: license-file
